<?xml version="1.0" encoding="UTF-8"?>
<objects serializationModel="Studio.02.02.00">
	<object class="AudioFile" id="{d3a22839-c383-4afc-8893-b1de2634cc0f}">
		<property name="assetPath">
			<value>Sounds/Footsteps/Mech-4.wav</value>
		</property>
		<property name="frequencyInKHz">
			<value>96</value>
		</property>
		<property name="channelCount">
			<value>2</value>
		</property>
		<property name="length">
			<value>1.3922291666666666</value>
		</property>
		<relationship name="masterAssetFolder">
			<destination>{57d937d1-16a0-49ac-a4ee-d5086543a020}</destination>
		</relationship>
	</object>
</objects>
